ftm_analyze/__init__.py
ftm_analyze/analysis/__init__.py
ftm_analyze/analysis/aggregate.py
ftm_analyze/analysis/analyzer.py
ftm_analyze/analysis/country.py
ftm_analyze/analysis/extract.py
ftm_analyze/analysis/ft_type_model.py
ftm_analyze/analysis/language.py
ftm_analyze/analysis/patterns.py
ftm_analyze/analysis/refine.py
ftm_analyze/analysis/util.py
ftm_analyze/annotate/__init__.py
ftm_analyze/annotate/annotator.py
ftm_analyze/annotate/symbols.py
ftm_analyze/annotate/tagger.py
ftm_analyze/cli.py
ftm_analyze/logic.py
ftm_analyze/settings.py
ftm_analyze/tasks.py
ftm_analyze-5.1.0.dist-info/METADATA
ftm_analyze-5.1.0.dist-info/WHEEL
ftm_analyze-5.1.0.dist-info/entry_points.txt
ftm_analyze-5.1.0.dist-info/licenses/LICENSE
ftm_analyze-5.1.0.dist-info/licenses/NOTICE
ftm_analyze-5.1.0.dist-info/RECORD
