Metadata-Version: 2.4
Name: ftm-analyze
Version: 5.1.0
Summary: Analyze FollowTheMoney entities
License: AGPLv3+
License-File: LICENSE
License-File: NOTICE
Author: Friedrich Lindenberg
Author-email: friedrich@pudo.org
Requires-Python: >=3.11,<3.15
Classifier: Intended Audience :: Developers
Classifier: Operating System :: OS Independent
Classifier: Programming Language :: Python
Classifier: Programming Language :: Python :: 3.11
Classifier: Programming Language :: Python :: 3.12
Classifier: Programming Language :: Python :: 3.13
Classifier: Programming Language :: Python :: 3.14
Provides-Extra: ner-flair
Provides-Extra: ner-spacy
Provides-Extra: ner-transformers
Provides-Extra: openaleph
Requires-Dist: anystore (>=0.4.1,<0.5.0)
Requires-Dist: cachetools (<6)
Requires-Dist: countrytagger (>=0.1.2,<0.2.0)
Requires-Dist: fasttext-numpy2 (>=0.10.4,<0.11.0)
Requires-Dist: flair (>=0.15.1,<0.16.0) ; extra == "ner-flair"
Requires-Dist: followthemoney (>=4.3.4,<5.0.0)
Requires-Dist: ftmq (>=4.3.4,<5.0.0)
Requires-Dist: geonames-tagger (>=1.0.1,<2.0.0)
Requires-Dist: juditha (>=4.2.2,<5.0.0)
Requires-Dist: openaleph-procrastinate (>=5.1.2,<6.0.0) ; extra == "openaleph"
Requires-Dist: openaleph-procrastinate (>=5.1.3,<6.0.0)
Requires-Dist: pydantic (>=2.11.7,<3.0.0)
Requires-Dist: pydantic-settings (>=2.9.1,<3.0.0)
Requires-Dist: rigour (>=1.5.0,<2.0.0)
Requires-Dist: schwifty (>=2025.9.0,<2026.0.0)
Requires-Dist: spacy (>=3.8.11,<4.0.0)
Requires-Dist: spacy (>=3.8.7,<4.0.0) ; extra == "ner-spacy"
Requires-Dist: transformers (>=4.57.1,<5.0.0) ; extra == "ner-transformers"
Project-URL: Documentation, https://docs.investigraph.dev/lib/ftm-analyze
Project-URL: Homepage, https://docs.investigraph.dev/lib/ftm-analyze
Project-URL: Issues, https://github.com/dataresearchcenter/ftm-analyze/issues
Project-URL: Repository, https://github.com/dataresearchcenter/ftm-analyze
